excludarr/__init__.py
excludarr/main.py
excludarr/version.py
excludarr/commands/__init__.py
excludarr/commands/providers.py
excludarr/commands/radarr.py
excludarr/commands/sonarr.py
excludarr/core/__init__.py
excludarr/core/radarr_actions.py
excludarr/core/sonarr_actions.py
excludarr/modules/__init__.py
excludarr/modules/justwatch/__init__.py
excludarr/modules/justwatch/base.py
excludarr/modules/justwatch/exceptions.py
excludarr/modules/justwatch/justwatch.py
excludarr/modules/pytmdb/__init__.py
excludarr/modules/pytmdb/base.py
excludarr/modules/pytmdb/exceptions.py
excludarr/modules/pytmdb/v3/__init__.py
excludarr/modules/pytmdb/v3/find.py
excludarr/modules/pytmdb/v3/movies.py
excludarr/modules/pytmdb/v3/tv.py
excludarr/utils/__init__.py
excludarr/utils/config.py
excludarr/utils/enums.py
excludarr/utils/filters.py
excludarr/utils/output.py
excludarr/utils/redact.py
excludarr-1.0.7.dist-info/LICENSE
excludarr-1.0.7.dist-info/METADATA
excludarr-1.0.7.dist-info/WHEEL
excludarr-1.0.7.dist-info/entry_points.txt
excludarr-1.0.7.dist-info/top_level.txt
excludarr-1.0.7.dist-info/RECORD
