Metadata-Version: 2.1
Name: excludarr
Version: 1.0.7
Summary: Excludarr excludes streaming services from Radarr and Sonarr
Home-page: https://github.com/haijeploeg/excludarr
Author: Haije Ploeg
Author-email: ploeg.haije@gmail.com
License: MIT
Project-URL: Bug Reports, https://github.com/haijeploeg/excludarr/issues
Project-URL: Source, https://github.com/haijeploeg/excludarr
Keywords: excludarr,radarr,sonarr,diskspace,cleanup,management,library,streaming,netflix
Classifier: Development Status :: 5 - Production/Stable
Classifier: Intended Audience :: Developers
Classifier: Topic :: Software Development :: Build Tools
Classifier: License :: OSI Approved :: MIT License
Classifier: Programming Language :: Python :: 3
Classifier: Programming Language :: Python :: 3.6
Classifier: Programming Language :: Python :: 3.7
Classifier: Programming Language :: Python :: 3.8
Classifier: Programming Language :: Python :: 3.9
Classifier: Programming Language :: Python :: 3.10
Classifier: Programming Language :: Python :: 3 :: Only
Requires-Python: >=3.6, <4
License-File: LICENSE
Requires-Dist: typer (>=0.4.1)
Requires-Dist: loguru (>=0.6.0)
Requires-Dist: rich (>=12.4.1)
Requires-Dist: requests (>=2.27.1)
Requires-Dist: PyYAML (>=6.0)
Requires-Dist: pyarr (>=3.1.3)
